setup.py
zengge/__init__.py
zengge.egg-info/PKG-INFO
zengge.egg-info/SOURCES.txt
zengge.egg-info/dependency_links.txt
zengge.egg-info/not-zip-safe
zengge.egg-info/top_level.txt