Metadata-Version: 1.1
Name: zengge
Version: 0.2
Summary: Python API for controlling Zengge LED bulbs
Home-page: http://github.com/mjg59/python-zengge
Author: Matthew Garrett
Author-email: mjg59@srcf.ucam.org
License: UNKNOWN
Platform: UNKNOWN
Classifier: Development Status :: 4 - Beta
Classifier: Intended Audience :: Developers
Classifier: License :: OSI Approved :: MIT License
Classifier: Operating System :: OS Independent
Classifier: Programming Language :: Python
